wagtailleafletwidget/__init__.py
wagtailleafletwidget/app_settings.py
wagtailleafletwidget/apps.py
wagtailleafletwidget/blocks.py
wagtailleafletwidget/edit_handlers.py
wagtailleafletwidget/helpers.py
wagtailleafletwidget/version.py
wagtailleafletwidget/widgets.py
wagtailleafletwidget/static/wagtailleafletwidget/css/geo-field.css
wagtailleafletwidget/static/wagtailleafletwidget/js/geo-field.js
wagtailleafletwidget/tests/__init__.py
wagtailleafletwidget/tests/test_geosgeometry_parser_helper.py
wagtailleafletwidget-1.0.3.dist-info/METADATA
wagtailleafletwidget-1.0.3.dist-info/WHEEL
wagtailleafletwidget-1.0.3.dist-info/top_level.txt
wagtailleafletwidget-1.0.3.dist-info/RECORD
